DeepTinbergen-0.0b0.dist-info/METADATA
DeepTinbergen-0.0b0.dist-info/RECORD
DeepTinbergen-0.0b0.dist-info/WHEEL
DeepTinbergen-0.0b0.dist-info/entry_points.txt
DeepTinbergen-0.0b0.dist-info/top_level.txt
deeptinbergen/__init__.py
deeptinbergen/version.py
