Metadata-Version: 2.1
Name: DeepTinbergen
Version: 0.0b0
Summary: abc
Home-page: https://github.com/AlexEMG/DeepTinbergen
Author: Alexander Mathis
Author-email: alexander.mathis@bethgelab.org
License: UNKNOWN
Platform: UNKNOWN
Classifier: Programming Language :: Python :: 3
Classifier: License :: OSI Approved :: GNU Lesser General Public License v3 (LGPLv3)
Classifier: Operating System :: OS Independent
Requires-Dist: easydict (~=1.7)
